Calculus/__init__.py
Calculus/DefiniteIntegral/__init__.py
Calculus/DefiniteIntegral/definite_integral.py
PyCalculus-1.0.1.dist-info/LICENSE
PyCalculus-1.0.1.dist-info/METADATA
PyCalculus-1.0.1.dist-info/WHEEL
PyCalculus-1.0.1.dist-info/top_level.txt
PyCalculus-1.0.1.dist-info/RECORD
